Workbook

Sheet README
A1: Month-End Bank Reconciliation & Close Dashboard
A2: Section | B2: Details
A3: Business Problem | B3: Accounting teams need to reconcile bank transactions to GL cash records and find unmatched items, timing differences, and amount variances.
A4: How to Use | B4: Replace the sample data with company exports, refresh formulas, review the Exceptions sheet, then present the Dashboard KPIs.
A5: Excel / Finance Skills Shown | B5: COUNTIF matching, helper sequence, INDEX/MATCH exception extraction, variance formulas, unmatched item flags, close dashboard, and exception reporting.

Sheet Bank_Statement
A1: Bank_ID | B1: Date | C1: Reference | D1: Description | E1: Bank_Amount | F1: Match_Key
A2: BNK-0001 | B2: 46159 | C2: REF-1001 | D2: Deposit | E2: -4477.35 | F2: =C2&"|"&ROUND(E2,2) -> REF-1001|-4477.35
A3: BNK-0002 | B3: 46150 | C3: REF-1002 | D3: Deposit | E3: -294.75 | F3: =C3&"|"&ROUND(E3,2) -> REF-1002|-294.75
A4: BNK-0003 | B4: 46144 | C4: REF-1003 | D4: Supplier Payment | E4: 11298.63 | F4: =C4&"|"&ROUND(E4,2) -> REF-1003|11298.63
A5: BNK-0004 | B5: 46147 | C5: REF-1004 | D5: Bank Fee | E5: -1676.9 | F5: =C5&"|"&ROUND(E5,2) -> REF-1004|-1676.9
A6: BNK-0005 | B6: 46165 | C6: REF-1005 | D6: Bank Fee | E6: -886.58 | F6: =C6&"|"&ROUND(E6,2) -> REF-1005|-886.58
A7: BNK-0006 | B7: 46163 | C7: REF-1006 | D7: Supplier Payment | E7: -2630.77 | F7: =C7&"|"&ROUND(E7,2) -> REF-1006|-2630.77
A8: BNK-0007 | B8: 46159 | C8: REF-1007 | D8: Customer EFT | E8: 3570.56 | F8: =C8&"|"&ROUND(E8,2) -> REF-1007|3570.56
A9: BNK-0008 | B9: 46153 | C9: REF-1008 | D9: Bank Fee | E9: -3319.95 | F9: =C9&"|"&ROUND(E9,2) -> REF-1008|-3319.95
A10: BNK-0009 | B10: 46149 | C10: REF-1009 | D10: Deposit | E10: 4438.93 | F10: =C10&"|"&ROUND(E10,2) -> REF-1009|4438.93
A11: BNK-0010 | B11: 46157 | C11: REF-1010 | D11: Bank Fee | E11: -666.72 | F11: =C11&"|"&ROUND(E11,2) -> REF-1010|-666.72
A12: BNK-0011 | B12: 46159 | C12: REF-1011 | D12: Customer EFT | E12: 12165 | F12: =C12&"|"&ROUND(E12,2) -> REF-1011|12165
A13: BNK-0012 | B13: 46167 | C13: REF-1012 | D13: Bank Fee | E13: -7280.51 | F13: =C13&"|"&ROUND(E13,2) -> REF-1012|-7280.51
... A121: BNK-0120 | B121: 46169 | C121: REF-1120 | D121: Supplier Payment | E121: -5028.61 | F121: =C121&"|"&ROUND(E121,2) -> REF-1120|-5028.61

Sheet GL_Cash_Book
A1: GL_ID | B1: Posting_Date | C1: Reference | D1: Description | E1: GL_Amount | F1: Match_Key | G1: Recon_Status | H1: Variance | I1: Exception_Seq
A2: GL-0001 | B2: 46164 | C2: REF-1001 | D2: Cash posting | E2: -4477.35 | F2: =C2&"|"&ROUND(E2,2) -> REF-1001|-4477.35 | G2: =IF(COUNTIF(Bank_Statement!$F:$F,F2)>0,"Matched","Unmatched GL Item") -> Matched | H2: =IF(G2="Matched",0,E2) -> 0 | I2: =IF(G2<>"Matched",COUNTIF($G$2:G2,"<>Matched"),"")
A3: GL-0002 | B3: 46157 | C3: REF-1002 | D3: Cash posting | E3: -294.75 | F3: =C3&"|"&ROUND(E3,2) -> REF-1002|-294.75 | G3: =IF(COUNTIF(Bank_Statement!$F:$F,F3)>0,"Matched","Unmatched GL Item") -> Matched | H3: =IF(G3="Matched",0,E3) -> 0 | I3: =IF(G3<>"Matched",COUNTIF($G$2:G3,"<>Matched"),"")
A4: GL-0003 | B4: 46159 | C4: REF-1003 | D4: Cash posting | E4: 11298.63 | F4: =C4&"|"&ROUND(E4,2) -> REF-1003|11298.63 | G4: =IF(COUNTIF(Bank_Statement!$F:$F,F4)>0,"Matched","Unmatched GL Item") -> Matched | H4: =IF(G4="Matched",0,E4) -> 0 | I4: =IF(G4<>"Matched",COUNTIF($G$2:G4,"<>Matched"),"")
A5: GL-0004 | B5: 46152 | C5: REF-1005 | D5: Cash posting | E5: -886.58 | F5: =C5&"|"&ROUND(E5,2) -> REF-1005|-886.58 | G5: =IF(COUNTIF(Bank_Statement!$F:$F,F5)>0,"Matched","Unmatched GL Item") -> Matched | H5: =IF(G5="Matched",0,E5) -> 0 | I5: =IF(G5<>"Matched",COUNTIF($G$2:G5,"<>Matched"),"")
A6: GL-0005 | B6: 46145 | C6: REF-1006 | D6: Cash posting | E6: -2630.77 | F6: =C6&"|"&ROUND(E6,2) -> REF-1006|-2630.77 | G6: =IF(COUNTIF(Bank_Statement!$F:$F,F6)>0,"Matched","Unmatched GL Item") -> Matched | H6: =IF(G6="Matched",0,E6) -> 0 | I6: =IF(G6<>"Matched",COUNTIF($G$2:G6,"<>Matched"),"")
A7: GL-0006 | B7: 46169 | C7: REF-1007 | D7: Cash posting | E7: 3570.56 | F7: =C7&"|"&ROUND(E7,2) -> REF-1007|3570.56 | G7: =IF(COUNTIF(Bank_Statement!$F:$F,F7)>0,"Matched","Unmatched GL Item") -> Matched | H7: =IF(G7="Matched",0,E7) -> 0 | I7: =IF(G7<>"Matched",COUNTIF($G$2:G7,"<>Matched"),"")
A8: GL-0007 | B8: 46150 | C8: REF-1008 | D8: Cash posting | E8: -3319.95 | F8: =C8&"|"&ROUND(E8,2) -> REF-1008|-3319.95 | G8: =IF(COUNTIF(Bank_Statement!$F:$F,F8)>0,"Matched","Unmatched GL Item") -> Matched | H8: =IF(G8="Matched",0,E8) -> 0 | I8: =IF(G8<>"Matched",COUNTIF($G$2:G8,"<>Matched"),"")
A9: GL-0008 | B9: 46173 | C9: REF-1009 | D9: Cash posting | E9: 4438.93 | F9: =C9&"|"&ROUND(E9,2) -> REF-1009|4438.93 | G9: =IF(COUNTIF(Bank_Statement!$F:$F,F9)>0,"Matched","Unmatched GL Item") -> Matched | H9: =IF(G9="Matched",0,E9) -> 0 | I9: =IF(G9<>"Matched",COUNTIF($G$2:G9,"<>Matched"),"")
A10: GL-0009 | B10: 46157 | C10: REF-1012 | D10: Cash posting | E10: -7280.51 | F10: =C10&"|"&ROUND(E10,2) -> REF-1012|-7280.51 | G10: =IF(COUNTIF(Bank_Statement!$F:$F,F10)>0,"Matched","Unmatched GL Item") -> Matched | H10: =IF(G10="Matched",0,E10) -> 0 | I10: =IF(G10<>"Matched",COUNTIF($G$2:G10,"<>Matched"),"")
A11: GL-0010 | B11: 46163 | C11: REF-1013 | D11: Cash posting | E11: -5234.09 | F11: =C11&"|"&ROUND(E11,2) -> REF-1013|-5234.09 | G11: =IF(COUNTIF(Bank_Statement!$F:$F,F11)>0,"Matched","Unmatched GL Item") -> Matched | H11: =IF(G11="Matched",0,E11) -> 0 | I11: =IF(G11<>"Matched",COUNTIF($G$2:G11,"<>Matched"),"")
A12: GL-0011 | B12: 46171 | C12: REF-1014 | D12: Cash posting | E12: 5342.67 | F12: =C12&"|"&ROUND(E12,2) -> REF-1014|5342.67 | G12: =IF(COUNTIF(Bank_Statement!$F:$F,F12)>0,"Matched","Unmatched GL Item") -> Unmatched GL Item | H12: =IF(G12="Matched",0,E12) -> 5342.67 | I12: =IF(G12<>"Matched",COUNTIF($G$2:G12,"<>Matched"),"") -> 1
A13: GL-0012 | B13: 46154 | C13: REF-1015 | D13: Cash posting | E13: -3432.75 | F13: =C13&"|"&ROUND(E13,2) -> REF-1015|-3432.75 | G13: =IF(COUNTIF(Bank_Statement!$F:$F,F13)>0,"Matched","Unmatched GL Item") -> Matched | H13: =IF(G13="Matched",0,E13) -> 0 | I13: =IF(G13<>"Matched",COUNTIF($G$2:G13,"<>Matched"),"")
... A116: GL-0115 | B116: 46153 | C116: GLONLY-115 | D116: Manual entry | E116: -3168.24 | F116: =C116&"|"&ROUND(E116,2) -> GLONLY-115|-3168.24 | G116: =IF(COUNTIF(Bank_Statement!$F:$F,F116)>0,"Matched","Unmatched GL Item") -> Unmatched GL Item | H116: =IF(G116="Matched",0,E116) -> -3168.24 | I116: =IF(G116<>"Matched",COUNTIF($G$2:G116,"<>Matched"),"") -> 35

Sheet Exceptions
A1: GL_ID | B1: Posting_Date | C1: Reference | D1: Description | E1: GL_Amount | F1: Match_Key | G1: Recon_Status | H1: Variance
A2: =IFERROR(INDEX(GL_Cash_Book!A$2:A$116,MATCH(ROW()-1,GL_Cash_Book!$I$2:$I$116,0)),"") -> GL-0011 | B2: =IFERROR(INDEX(GL_Cash_Book!B$2:B$116,MATCH(ROW()-1,GL_Cash_Book!$I$2:$I$116,0)),"") -> 46171 | C2: =IFERROR(INDEX(GL_Cash_Book!C$2:C$116,MATCH(ROW()-1,GL_Cash_Book!$I$2:$I$116,0)),"") -> REF-1014 | D2: =IFERROR(INDEX(GL_Cash_Book!D$2:D$116,MATCH(ROW()-1,GL_Cash_Book!$I$2:$I$116,0)),"") -> Cash posting | E2: =IFERROR(INDEX(GL_Cash_Book!E$2:E$116,MATCH(ROW()-1,GL_Cash_Book!$I$2:$I$116,0)),"") -> 5342.67 | F2: =IFERROR(INDEX(GL_Cash_Book!F$2:F$116,MATCH(ROW()-1,GL_Cash_Book!$I$2:$I$116,0)),"") -> REF-1014|5342.67 | G2: =IFERROR(INDEX(GL_Cash_Book!G$2:G$116,MATCH(ROW()-1,GL_Cash_Book!$I$2:$I$116,0)),"") -> Unmatched GL Item | H2: =IFERROR(INDEX(GL_Cash_Book!H$2:H$116,MATCH(ROW()-1,GL_Cash_Book!$I$2:$I$116,0)),"") -> 5342.67
A3: =IFERROR(INDEX(GL_Cash_Book!A$2:A$116,MATCH(ROW()-1,GL_Cash_Book!$I$2:$I$116,0)),"") -> GL-0017 | B3: =IFERROR(INDEX(GL_Cash_Book!B$2:B$116,MATCH(ROW()-1,GL_Cash_Book!$I$2:$I$116,0)),"") -> 46153 | C3: =IFERROR(INDEX(GL_Cash_Book!C$2:C$116,MATCH(ROW()-1,GL_Cash_Book!$I$2:$I$116,0)),"") -> REF-1021 | D3: =IFERROR(INDEX(GL_Cash_Book!D$2:D$116,MATCH(ROW()-1,GL_Cash_Book!$I$2:$I$116,0)),"") -> Cash posting | E3: =IFERROR(INDEX(GL_Cash_Book!E$2:E$116,MATCH(ROW()-1,GL_Cash_Book!$I$2:$I$116,0)),"") -> -7539.57 | F3: =IFERROR(INDEX(GL_Cash_Book!F$2:F$116,MATCH(ROW()-1,GL_Cash_Book!$I$2:$I$116,0)),"") -> REF-1021|-7539.57 | G3: =IFERROR(INDEX(GL_Cash_Book!G$2:G$116,MATCH(ROW()-1,GL_Cash_Book!$I$2:$I$116,0)),"") -> Unmatched GL Item | H3: =IFERROR(INDEX(GL_Cash_Book!H$2:H$116,MATCH(ROW()-1,GL_Cash_Book!$I$2:$I$116,0)),"") -> -7539.57
A4: =IFERROR(INDEX(GL_Cash_Book!A$2:A$116,MATCH(ROW()-1,GL_Cash_Book!$I$2:$I$116,0)),"") -> GL-0019 | B4: =IFERROR(INDEX(GL_Cash_Book!B$2:B$116,MATCH(ROW()-1,GL_Cash_Book!$I$2:$I$116,0)),"") -> 46143 | C4: =IFERROR(INDEX(GL_Cash_Book!C$2:C$116,MATCH(ROW()-1,GL_Cash_Book!$I$2:$I$116,0)),"") -> REF-1023 | D4: =IFERROR(INDEX(GL_Cash_Book!D$2:D$116,MATCH(ROW()-1,GL_Cash_Book!$I$2:$I$116,0)),"") -> Cash posting | E4: =IFERROR(INDEX(GL_Cash_Book!E$2:E$116,MATCH(ROW()-1,GL_Cash_Book!$I$2:$I$116,0)),"") -> -711.91 | F4: =IFERROR(INDEX(GL_Cash_Book!F$2:F$116,MATCH(ROW()-1,GL_Cash_Book!$I$2:$I$116,0)),"") -> REF-1023|-711.91 | G4: =IFERROR(INDEX(GL_Cash_Book!G$2:G$116,MATCH(ROW()-1,GL_Cash_Book!$I$2:$I$116,0)),"") -> Unmatched GL Item | H4: =IFERROR(INDEX(GL_Cash_Book!H$2:H$116,MATCH(ROW()-1,GL_Cash_Book!$I$2:$I$116,0)),"") -> -711.91
A5: =IFERROR(INDEX(GL_Cash_Book!A$2:A$116,MATCH(ROW()-1,GL_Cash_Book!$I$2:$I$116,0)),"") -> GL-0022 | B5: =IFERROR(INDEX(GL_Cash_Book!B$2:B$116,MATCH(ROW()-1,GL_Cash_Book!$I$2:$I$116,0)),"") -> 46146 | C5: =IFERROR(INDEX(GL_Cash_Book!C$2:C$116,MATCH(ROW()-1,GL_Cash_Book!$I$2:$I$116,0)),"") -> REF-1026 | D5: =IFERROR(INDEX(GL_Cash_Book!D$2:D$116,MATCH(ROW()-1,GL_Cash_Book!$I$2:$I$116,0)),"") -> Cash posting | E5: =IFERROR(INDEX(GL_Cash_Book!E$2:E$116,MATCH(ROW()-1,GL_Cash_Book!$I$2:$I$116,0)),"") -> -1278.44 | F5: =IFERROR(INDEX(GL_Cash_Book!F$2:F$116,MATCH(ROW()-1,GL_Cash_Book!$I$2:$I$116,0)),"") -> REF-1026|-1278.44 | G5: =IFERROR(INDEX(GL_Cash_Book!G$2:G$116,MATCH(ROW()-1,GL_Cash_Book!$I$2:$I$116,0)),"") -> Unmatched GL Item | H5: =IFERROR(INDEX(GL_Cash_Book!H$2:H$116,MATCH(ROW()-1,GL_Cash_Book!$I$2:$I$116,0)),"") -> -1278.44
A6: =IFERROR(INDEX(GL_Cash_Book!A$2:A$116,MATCH(ROW()-1,GL_Cash_Book!$I$2:$I$116,0)),"") -> GL-0027 | B6: =IFERROR(INDEX(GL_Cash_Book!B$2:B$116,MATCH(ROW()-1,GL_Cash_Book!$I$2:$I$116,0)),"") -> 46149 | C6: =IFERROR(INDEX(GL_Cash_Book!C$2:C$116,MATCH(ROW()-1,GL_Cash_Book!$I$2:$I$116,0)),"") -> REF-1031 | D6: =IFERROR(INDEX(GL_Cash_Book!D$2:D$116,MATCH(ROW()-1,GL_Cash_Book!$I$2:$I$116,0)),"") -> Cash posting | E6: =IFERROR(INDEX(GL_Cash_Book!E$2:E$116,MATCH(ROW()-1,GL_Cash_Book!$I$2:$I$116,0)),"") -> 8775.73 | F6: =IFERROR(INDEX(GL_Cash_Book!F$2:F$116,MATCH(ROW()-1,GL_Cash_Book!$I$2:$I$116,0)),"") -> REF-1031|8775.73 | G6: =IFERROR(INDEX(GL_Cash_Book!G$2:G$116,MATCH(ROW()-1,GL_Cash_Book!$I$2:$I$116,0)),"") -> Unmatched GL Item | H6: =IFERROR(INDEX(GL_Cash_Book!H$2:H$116,MATCH(ROW()-1,GL_Cash_Book!$I$2:$I$116,0)),"") -> 8775.73
A7: =IFERROR(INDEX(GL_Cash_Book!A$2:A$116,MATCH(ROW()-1,GL_Cash_Book!$I$2:$I$116,0)),"") -> GL-0030 | B7: =IFERROR(INDEX(GL_Cash_Book!B$2:B$116,MATCH(ROW()-1,GL_Cash_Book!$I$2:$I$116,0)),"") -> 46160 | C7: =IFERROR(INDEX(GL_Cash_Book!C$2:C$116,MATCH(ROW()-1,GL_Cash_Book!$I$2:$I$116,0)),"") -> REF-1035 | D7: =IFERROR(INDEX(GL_Cash_Book!D$2:D$116,MATCH(ROW()-1,GL_Cash_Book!$I$2:$I$116,0)),"") -> Cash posting | E7: =IFERROR(INDEX(GL_Cash_Book!E$2:E$116,MATCH(ROW()-1,GL_Cash_Book!$I$2:$I$116,0)),"") -> 10944.89 | F7: =IFERROR(INDEX(GL_Cash_Book!F$2:F$116,MATCH(ROW()-1,GL_Cash_Book!$I$2:$I$116,0)),"") -> REF-1035|10944.89 | G7: =IFERROR(INDEX(GL_Cash_Book!G$2:G$116,MATCH(ROW()-1,GL_Cash_Book!$I$2:$I$116,0)),"") -> Unmatched GL Item | H7: =IFERROR(INDEX(GL_Cash_Book!H$2:H$116,MATCH(ROW()-1,GL_Cash_Book!$I$2:$I$116,0)),"") -> 10944.89
A8: =IFERROR(INDEX(GL_Cash_Book!A$2:A$116,MATCH(ROW()-1,GL_Cash_Book!$I$2:$I$116,0)),"") -> GL-0033 | B8: =IFERROR(INDEX(GL_Cash_Book!B$2:B$116,MATCH(ROW()-1,GL_Cash_Book!$I$2:$I$116,0)),"") -> 46143 | C8: =IFERROR(INDEX(GL_Cash_Book!C$2:C$116,MATCH(ROW()-1,GL_Cash_Book!$I$2:$I$116,0)),"") -> REF-1038 | D8: =IFERROR(INDEX(GL_Cash_Book!D$2:D$116,MATCH(ROW()-1,GL_Cash_Book!$I$2:$I$116,0)),"") -> Cash posting | E8: =IFERROR(INDEX(GL_Cash_Book!E$2:E$116,MATCH(ROW()-1,GL_Cash_Book!$I$2:$I$116,0)),"") -> -5335.12 | F8: =IFERROR(INDEX(GL_Cash_Book!F$2:F$116,MATCH(ROW()-1,GL_Cash_Book!$I$2:$I$116,0)),"") -> REF-1038|-5335.12 | G8: =IFERROR(INDEX(GL_Cash_Book!G$2:G$116,MATCH(ROW()-1,GL_Cash_Book!$I$2:$I$116,0)),"") -> Unmatched GL Item | H8: =IFERROR(INDEX(GL_Cash_Book!H$2:H$116,MATCH(ROW()-1,GL_Cash_Book!$I$2:$I$116,0)),"") -> -5335.12
A9: =IFERROR(INDEX(GL_Cash_Book!A$2:A$116,MATCH(ROW()-1,GL_Cash_Book!$I$2:$I$116,0)),"") -> GL-0041 | B9: =IFERROR(INDEX(GL_Cash_Book!B$2:B$116,MATCH(ROW()-1,GL_Cash_Book!$I$2:$I$116,0)),"") -> 46146 | C9: =IFERROR(INDEX(GL_Cash_Book!C$2:C$116,MATCH(ROW()-1,GL_Cash_Book!$I$2:$I$116,0)),"") -> REF-1049 | D9: =IFERROR(INDEX(GL_Cash_Book!D$2:D$116,MATCH(ROW()-1,GL_Cash_Book!$I$2:$I$116,0)),"") -> Cash posting | E9: =IFERROR(INDEX(GL_Cash_Book!E$2:E$116,MATCH(ROW()-1,GL_Cash_Book!$I$2:$I$116,0)),"") -> 3518.66 | F9: =IFERROR(INDEX(GL_Cash_Book!F$2:F$116,MATCH(ROW()-1,GL_Cash_Book!$I$2:$I$116,0)),"") -> REF-1049|3518.66 | G9: =IFERROR(INDEX(GL_Cash_Book!G$2:G$116,MATCH(ROW()-1,GL_Cash_Book!$I$2:$I$116,0)),"") -> Unmatched GL Item | H9: =IFERROR(INDEX(GL_Cash_Book!H$2:H$116,MATCH(ROW()-1,GL_Cash_Book!$I$2:$I$116,0)),"") -> 3518.66
A10: =IFERROR(INDEX(GL_Cash_Book!A$2:A$116,MATCH(ROW()-1,GL_Cash_Book!$I$2:$I$116,0)),"") -> GL-0045 | B10: =IFERROR(INDEX(GL_Cash_Book!B$2:B$116,MATCH(ROW()-1,GL_Cash_Book!$I$2:$I$116,0)),"") -> 46149 | C10: =IFERROR(INDEX(GL_Cash_Book!C$2:C$116,MATCH(ROW()-1,GL_Cash_Book!$I$2:$I$116,0)),"") -> REF-1053 | D10: =IFERROR(INDEX(GL_Cash_Book!D$2:D$116,MATCH(ROW()-1,GL_Cash_Book!$I$2:$I$116,0)),"") -> Cash posting | E10: =IFERROR(INDEX(GL_Cash_Book!E$2:E$116,MATCH(ROW()-1,GL_Cash_Book!$I$2:$I$116,0)),"") -> -6941.29 | F10: =IFERROR(INDEX(GL_Cash_Book!F$2:F$116,MATCH(ROW()-1,GL_Cash_Book!$I$2:$I$116,0)),"") -> REF-1053|-6941.29 | G10: =IFERROR(INDEX(GL_Cash_Book!G$2:G$116,MATCH(ROW()-1,GL_Cash_Book!$I$2:$I$116,0)),"") -> Unmatched GL Item | H10: =IFERROR(INDEX(GL_Cash_Book!H$2:H$116,MATCH(ROW()-1,GL_Cash_Book!$I$2:$I$116,0)),"") -> -6941.29
A11: =IFERROR(INDEX(GL_Cash_Book!A$2:A$116,MATCH(ROW()-1,GL_Cash_Book!$I$2:$I$116,0)),"") -> GL-0056 | B11: =IFERROR(INDEX(GL_Cash_Book!B$2:B$116,MATCH(ROW()-1,GL_Cash_Book!$I$2:$I$116,0)),"") -> 46169 | C11: =IFERROR(INDEX(GL_Cash_Book!C$2:C$116,MATCH(ROW()-1,GL_Cash_Book!$I$2:$I$116,0)),"") -> REF-1066 | D11: =IFERROR(INDEX(GL_Cash_Book!D$2:D$116,MATCH(ROW()-1,GL_Cash_Book!$I$2:$I$116,0)),"") -> Cash posting | E11: =IFERROR(INDEX(GL_Cash_Book!E$2:E$116,MATCH(ROW()-1,GL_Cash_Book!$I$2:$I$116,0)),"") -> 4371.38 | F11: =IFERROR(INDEX(GL_Cash_Book!F$2:F$116,MATCH(ROW()-1,GL_Cash_Book!$I$2:$I$116,0)),"") -> REF-1066|4371.38 | G11: =IFERROR(INDEX(GL_Cash_Book!G$2:G$116,MATCH(ROW()-1,GL_Cash_Book!$I$2:$I$116,0)),"") -> Unmatched GL Item | H11: =IFERROR(INDEX(GL_Cash_Book!H$2:H$116,MATCH(ROW()-1,GL_Cash_Book!$I$2:$I$116,0)),"") -> 4371.38
A12: =IFERROR(INDEX(GL_Cash_Book!A$2:A$116,MATCH(ROW()-1,GL_Cash_Book!$I$2:$I$116,0)),"") -> GL-0061 | B12: =IFERROR(INDEX(GL_Cash_Book!B$2:B$116,MATCH(ROW()-1,GL_Cash_Book!$I$2:$I$116,0)),"") -> 46168 | C12: =IFERROR(INDEX(GL_Cash_Book!C$2:C$116,MATCH(ROW()-1,GL_Cash_Book!$I$2:$I$116,0)),"") -> REF-1072 | D12: =IFERROR(INDEX(GL_Cash_Book!D$2:D$116,MATCH(ROW()-1,GL_Cash_Book!$I$2:$I$116,0)),"") -> Cash posting | E12: =IFERROR(INDEX(GL_Cash_Book!E$2:E$116,MATCH(ROW()-1,GL_Cash_Book!$I$2:$I$116,0)),"") -> -3832.13 | F12: =IFERROR(INDEX(GL_Cash_Book!F$2:F$116,MATCH(ROW()-1,GL_Cash_Book!$I$2:$I$116,0)),"") -> REF-1072|-3832.13 | G12: =IFERROR(INDEX(GL_Cash_Book!G$2:G$116,MATCH(ROW()-1,GL_Cash_Book!$I$2:$I$116,0)),"") -> Unmatched GL Item | H12: =IFERROR(INDEX(GL_Cash_Book!H$2:H$116,MATCH(ROW()-1,GL_Cash_Book!$I$2:$I$116,0)),"") -> -3832.13
A13: =IFERROR(INDEX(GL_Cash_Book!A$2:A$116,MATCH(ROW()-1,GL_Cash_Book!$I$2:$I$116,0)),"") -> GL-0065 | B13: =IFERROR(INDEX(GL_Cash_Book!B$2:B$116,MATCH(ROW()-1,GL_Cash_Book!$I$2:$I$116,0)),"") -> 46158 | C13: =IFERROR(INDEX(GL_Cash_Book!C$2:C$116,MATCH(ROW()-1,GL_Cash_Book!$I$2:$I$116,0)),"") -> REF-1077 | D13: =IFERROR(INDEX(GL_Cash_Book!D$2:D$116,MATCH(ROW()-1,GL_Cash_Book!$I$2:$I$116,0)),"") -> Cash posting | E13: =IFERROR(INDEX(GL_Cash_Book!E$2:E$116,MATCH(ROW()-1,GL_Cash_Book!$I$2:$I$116,0)),"") -> -3001.39 | F13: =IFERROR(INDEX(GL_Cash_Book!F$2:F$116,MATCH(ROW()-1,GL_Cash_Book!$I$2:$I$116,0)),"") -> REF-1077|-3001.39 | G13: =IFERROR(INDEX(GL_Cash_Book!G$2:G$116,MATCH(ROW()-1,GL_Cash_Book!$I$2:$I$116,0)),"") -> Unmatched GL Item | H13: =IFERROR(INDEX(GL_Cash_Book!H$2:H$116,MATCH(ROW()-1,GL_Cash_Book!$I$2:$I$116,0)),"") -> -3001.39
... A116: =IFERROR(INDEX(GL_Cash_Book!A$2:A$116,MATCH(ROW()-1,GL_Cash_Book!$I$2:$I$116,0)),"") | B116: =IFERROR(INDEX(GL_Cash_Book!B$2:B$116,MATCH(ROW()-1,GL_Cash_Book!$I$2:$I$116,0)),"") | C116: =IFERROR(INDEX(GL_Cash_Book!C$2:C$116,MATCH(ROW()-1,GL_Cash_Book!$I$2:$I$116,0)),"") | D116: =IFERROR(INDEX(GL_Cash_Book!D$2:D$116,MATCH(ROW()-1,GL_Cash_Book!$I$2:$I$116,0)),"") | E116: =IFERROR(INDEX(GL_Cash_Book!E$2:E$116,MATCH(ROW()-1,GL_Cash_Book!$I$2:$I$116,0)),"") | F116: =IFERROR(INDEX(GL_Cash_Book!F$2:F$116,MATCH(ROW()-1,GL_Cash_Book!$I$2:$I$116,0)),"") | G116: =IFERROR(INDEX(GL_Cash_Book!G$2:G$116,MATCH(ROW()-1,GL_Cash_Book!$I$2:$I$116,0)),"") | H116: =IFERROR(INDEX(GL_Cash_Book!H$2:H$116,MATCH(ROW()-1,GL_Cash_Book!$I$2:$I$116,0)),"")

Sheet Dashboard
A1: Bank Reconciliation Dashboard
A2: Self-directed portfolio project with realistic sample data, formulas, controls, and dashboard
A4: KPI | B4: Value | D4: Category | E4: Value
A5: Bank Balance | B5: =SUM(Bank_Statement!$E$2:$E$121) -> 415116.84 | D5: Matched | E5: =COUNTIF(GL_Cash_Book!$G:$G,"Matched") -> 80
A6: GL Balance | B6: =SUM(GL_Cash_Book!$E$2:$E$116) -> 314225.17 | D6: Unmatched GL Item | E6: =COUNTIF(GL_Cash_Book!$G:$G,"Unmatched GL Item") -> 35
A7: Difference | B7: =B5-B6 -> 100891.67
A8: Matched GL Items | B8: =COUNTIF(GL_Cash_Book!$G:$G,"Matched") -> 80
A9: Unmatched GL Items | B9: =COUNTIF(GL_Cash_Book!$G:$G,"Unmatched GL Item") -> 35
